README.md
setup.cfg
setup.py
boom/__init__.py
boom/api.py
boom/conversation.py
boom/encoder.py
boom/models.py
boom/order.py
boom/pay.py
boom_sdk.egg-info/PKG-INFO
boom_sdk.egg-info/SOURCES.txt
boom_sdk.egg-info/dependency_links.txt
boom_sdk.egg-info/requires.txt
boom_sdk.egg-info/top_level.txt