Metadata-Version: 1.1
Name: boom-sdk
Version: 0.3.1
Summary: SDK for interacting with Boom
Home-page: https://github.com/boomletsgo/boom-sdk-python
Author: Jordan Ambra
Author-email: jordan@serenitysoftware.io
License: The Unlicense
Keywords: boom
Platform: UNKNOWN
Classifier: Development Status :: 5 - Production/Stable
Classifier: Intended Audience :: Developers
Classifier: Operating System :: OS Independent
Classifier: Programming Language :: Python
Classifier: Programming Language :: Python :: 2
Classifier: Programming Language :: Python :: 2.6
Classifier: Programming Language :: Python :: 2.7
Classifier: Programming Language :: Python :: 3
Classifier: Programming Language :: Python :: 3.4
Classifier: Programming Language :: Python :: 3.5
Classifier: Programming Language :: Python :: 3.6
Classifier: Topic :: Software Development :: Libraries
